pyimof/__init__.py
pyimof/display.py
pyimof/io.py
pyimof/solvers.py
pyimof/util.py
pyimof/data/__init__.py
pyimof/data/Beanbags/frame10.png
pyimof/data/Beanbags/frame11.png
pyimof/data/Dimetrodon/frame10.png
pyimof/data/Dimetrodon/frame11.png
pyimof/data/DogDance/frame10.png
pyimof/data/DogDance/frame11.png
pyimof/data/Grove2/frame10.png
pyimof/data/Grove2/frame11.png
pyimof/data/Grove3/frame10.png
pyimof/data/Grove3/frame11.png
pyimof/data/Hydrangea/frame10.png
pyimof/data/Hydrangea/frame11.png
pyimof/data/MiniCooper/frame10.png
pyimof/data/MiniCooper/frame11.png
pyimof/data/RubberWhale/frame10.png
pyimof/data/RubberWhale/frame11.png
pyimof/data/Urban2/frame10.png
pyimof/data/Urban2/frame11.png
pyimof/data/Urban3/frame10.png
pyimof/data/Urban3/frame11.png
pyimof/data/Venus/frame10.png
pyimof/data/Venus/frame11.png
pyimof/data/Walking/frame10.png
pyimof/data/Walking/frame11.png
pyimof/data/Yosemite/frame10.png
pyimof/data/Yosemite/frame11.png
pyimof-1.0.0.dist-info/LICENSE
pyimof-1.0.0.dist-info/METADATA
pyimof-1.0.0.dist-info/WHEEL
pyimof-1.0.0.dist-info/top_level.txt
pyimof-1.0.0.dist-info/RECORD
